commandt/score.cpython-36m-darwin.so
commandt.score-0.1.2.dist-info/DESCRIPTION.rst
commandt.score-0.1.2.dist-info/METADATA
commandt.score-0.1.2.dist-info/RECORD
commandt.score-0.1.2.dist-info/WHEEL
commandt.score-0.1.2.dist-info/metadata.json
commandt.score-0.1.2.dist-info/top_level.txt
