Metadata-Version: 2.0
Name: commandt.score
Version: 0.1.2
Summary: Command-T fuzzy match scoring algorithm
Home-page: https://github.com/wincent/command-t/tree/python/score
Author: Greg Hurrell
Author-email: greg@hurrell.net
License: BSD
Platform: UNKNOWN
Classifier: Development Status :: 3 - Alpha
Classifier: Intended Audience :: Developers
Classifier: License :: OSI Approved :: BSD License
Classifier: Operating System :: MacOS :: MacOS X
Classifier: Operating System :: POSIX
Classifier: Programming Language :: C
Classifier: Programming Language :: Python :: 3 :: Only
